[
	{
		"name" : "Altarget-Rebuild",
		"file" : "altarget",
		"extension" : "ipf",
		"fileVersion" : "v1.2.0",
		"releaseTag" : "altarget",
		"unicode" : "⛄",
		"updateInfo":"added dynamic color change based on monsters current hp",
		"description" : "continuation of altarget addon by torahamu post-re:build",
		"tags" : [
			"target"
		]
	},
	{
		"name" : "Bookmarkwarp-Rebuild",
		"file" : "bookmarkwarp",
		"extension" : "ipf",
		"fileVersion" : "v1.0.2",
		"releaseTag" : "bookmarkwarp",
		"unicode" : "⛄",
		"updateInfo":"fixed not being able to drag ui and not being able to remove bookmark",
		"description" : "continuation of bookmarkwarp addon by pocon307 post-re:build",
		"tags" : [
			"warp"
		]
	},
	{
		"name" : "CDtracker-Rebuild",
		"file" : "cdtracker",
		"extension" : "ipf",
		"fileVersion" : "v1.0.2",
		"releaseTag" : "cdtracker",
		"unicode" : "⛄",
		"updateInfo":"fixed yellow text not showing after 19/02/19 update. fixed not being able to leave set message blank",
		"description" : "continuation of cdtracker addon byaxjv post-re:build",
		"tags" : [
			"cooldown",
			"cd"
		]
	}
]
